{
  "products": [
    {
      "id": "kp-wd-sn850x",
      "name": "WD_BLACK SN850X NVMe SSD",
      "category": "Storage",
      "price": 249.99,
      "description": "Crush load times and slash throttling, lagging, and texture pop-ins with the WD_BLACK SN850X NVMe SSD. Built for top-tier performance with 7,300MB/s speeds.",
      "image": "resources/8TB_SSD_NVMe.png",
      "specs": {
        "capacity": "8TB",
        "speed": "7,300 MB/s",
        "features": "Game Mode 2.0, DirectStorage",
        "interface": "PCIe Gen4 x4"
      },
      "tag": "NEW RELEASE",
      "rating": 4.9,
      "reviews": 1204,
      "stock": 45,
      "isActive": true,
      "longDescription": "Insane speeds up to 7,300 MB/s deliver top-tier performance with ridiculously short load times — for the elite gaming experience you’ve been waiting for. All capacities have an optional heatsink version that's not only eye-catching, but also helps your rig maintain peak performance through your most intense gaming sessions."
    },
    {
      "id": "kp-k98m-keys",
      "name": "Alto Keys K98M Mechanical Keyboard",
      "category": "Peripherals",
      "price": 149.99,
      "description": "A wireless mechanical keyboard with UniCushion gasket that absorbs vibration to enhance the rich, satisfying sound of each keystroke.",
      "image": "resources/Alto_Keys_K98M_mechanical_keyboard.png",
      "specs": {
        "connectivity": "Logi Bolt / Bluetooth",
        "layout": "98-key",
        "battery": "12 months (Rechargeable)",
        "backlighting": "White LED"
      },
      "tag": "IN STOCK",
      "rating": 4.8,
      "reviews": 320,
      "stock": 100,
      "isActive": true,
      "longDescription": "Transform your workspace into a place of tactile and auditory inspiration. Easy-switch up to 3 devices simultaneously."
    },
    {
      "id": "kp-g502-plus",
      "name": "Logitech G502 X PLUS",
      "category": "Peripherals",
      "price": 159.99,
      "description": "Reinvented with first-ever LIGHTFORCE hybrid switches, LIGHTSPEED pro-grade wireless, LIGHTSYNC RGB, and HERO 25K sensor.",
      "image": "resources/G502_Logitech_mouse.png",
      "specs": {
        "sensor": "HERO 25K (25,600 DPI)",
        "weight": "106g",
        "battery": "130 hrs",
        "lighting": "8-zone RGB"
      },
      "tag": "IN STOCK",
      "rating": 4.9,
      "reviews": 2341,
      "stock": 210,
      "isActive": true,
      "longDescription": "The latest addition to the legendary G502 lineage. Unleash unbridled high-performance precision."
    },
    {
      "id": "kp-m4-hub",
      "name": "Satechi Mac mini M4 Hub & Stand",
      "category": "Accessories",
      "price": 99.99,
      "description": "Expand your Mac Mini M4 capabilities with NVMe SSD enclosure and 5-in-1 Expansion Ports.",
      "image": "resources/M2_Mac_mini.png",
      "specs": {
        "ports": "2x USB-A 10Gbps, SD UHS-II",
        "storageSupport": "Up to 4TB NVMe SSD",
        "cooling": "Optimized Self-Cooling",
        "material": "Industry-grade aluminum"
      },
      "tag": "POPULAR",
      "rating": 4.6,
      "reviews": 115,
      "stock": 35,
      "isActive": true,
      "longDescription": "Crafted to seamlessly match your Mac Mini M4, this hub combines durability with a slim, micro design that fits perfectly with the aesthetic."
    },
    {
      "id": "kp-rtx-3050",
      "name": "MSI GeForce RTX 3050 Ventus 2X",
      "category": "Graphics",
      "price": 299.99,
      "description": "Dual Fan Thermal Design featuring TORX Fan 3.0 and Zero Frozr technology for extreme silent operation.",
      "image": "resources/RTX3050.png",
      "specs": {
        "memory": "6GB GDDR6 (192-bit)",
        "clock": "1492 MHz Boost",
        "ports": "3x DP, 1x HDMI 2.1",
        "features": "Zero Frozr, TORX 3.0"
      },
      "tag": "LOW STOCK",
      "rating": 4.4,
      "reviews": 89,
      "stock": 12,
      "isActive": true,
      "longDescription": "NVIDIA GeForce RTX 3050 brings power and performance with MSI's robust cooling thermal design."
    },
    {
      "id": "kp-a14-99x",
      "name": "Kinetic Air 14\"",
      "category": "Laptops & Mobiles",
      "price": 1299,
      "description": "Unleash studio-grade performance on the go. M2 Ultra architecture.",
      "image": "https://placehold.co/600x400/0f172a/FFF?text=Kinetic+Air+14",
      "specs": {
        "memory": "16GB Unified",
        "storage": "512GB SSD",
        "cpu": "M-Series Advanced"
      },
      "tag": "",
      "rating": 4.5,
      "reviews": 120,
      "stock": 50,
      "isActive": true,
      "longDescription": "Our flagship ultra-portable chassis."
    }
  ]
}
